odoo/addons/repair_order_mass_validate/README.rst
odoo/addons/repair_order_mass_validate/__init__.py
odoo/addons/repair_order_mass_validate/__manifest__.py
odoo/addons/repair_order_mass_validate/models/__init__.py
odoo/addons/repair_order_mass_validate/models/repair_order.py
odoo/addons/repair_order_mass_validate/readme/CONTRIBUTORS.rst
odoo/addons/repair_order_mass_validate/readme/DESCRIPTION.rst
odoo/addons/repair_order_mass_validate/readme/USAGE.rst
odoo/addons/repair_order_mass_validate/security/ir.model.access.csv
odoo/addons/repair_order_mass_validate/static/description/icon.png
odoo/addons/repair_order_mass_validate/static/description/index.html
odoo/addons/repair_order_mass_validate/tests/__init__.py
odoo/addons/repair_order_mass_validate/tests/test_repair_order_mass_validate.py
odoo/addons/repair_order_mass_validate/wizard/__init__.py
odoo/addons/repair_order_mass_validate/wizard/repair_order_mass_complete_wizard.py
odoo/addons/repair_order_mass_validate/wizard/repair_order_mass_complete_wizard_views.xml
odoo_addon_repair_order_mass_validate-16.0.1.0.0.1.dist-info/METADATA
odoo_addon_repair_order_mass_validate-16.0.1.0.0.1.dist-info/WHEEL
odoo_addon_repair_order_mass_validate-16.0.1.0.0.1.dist-info/top_level.txt
odoo_addon_repair_order_mass_validate-16.0.1.0.0.1.dist-info/RECORD
