Metadata-Version: 2.1
Name: odoo-addon-repair_order_mass_validate
Version: 16.0.1.0.0.1
Summary: Repair Order Mass Validate
Home-page: https://github.com/sygel-technology/sy-repair
Author: Sygel,Odoo Community Association (OCA)
Author-email: support@odoo-community.org
License: AGPL-3
Classifier: Programming Language :: Python
Classifier: Framework :: Odoo
Classifier: Framework :: Odoo :: 16.0
Classifier: License :: OSI Approved :: GNU Affero General Public License v3
Requires-Python: >=3.10
Requires-Dist: odoo<16.1dev,>=16.0a
